[
  {
    "fields": [
      {
        "validation": [
          {
            "rules": [
              {
                "flag": "presence",
                "constraint": "required"
              }
            ],
            "level": "error"
          }
        ],
        "name": "companyName",
        "type": "string"
      },
      {
        "name": "tagline",
        "type": "string"
      },
      {
        "name": "phone",
        "type": "string"
      },
      {
        "name": "email",
        "type": "string"
      },
      {
        "name": "address",
        "type": "text"
      },
      {
        "of": [
          {
            "fields": [
              {
                "validation": [
                  {
                    "rules": [
                      {
                        "flag": "presence",
                        "constraint": "required"
                      }
                    ],
                    "level": "error"
                  }
                ],
                "name": "platform",
                "type": "string"
              },
              {
                "validation": [
                  {
                    "rules": [
                      {
                        "flag": "uri",
                        "constraint": {
                          "options": {
                            "scheme": [
                              "/^http$/",
                              "/^https$/"
                            ],
                            "allowRelative": false,
                            "relativeOnly": false,
                            "allowCredentials": false
                          }
                        }
                      },
                      {
                        "flag": "presence",
                        "constraint": "required"
                      }
                    ],
                    "level": "error"
                  }
                ],
                "name": "url",
                "type": "url",
                "title": "URL"
              }
            ],
            "type": "object"
          }
        ],
        "name": "socialLinks",
        "type": "array"
      }
    ],
    "name": "siteSettings",
    "type": "document"
  },
  {
    "fields": [
      {
        "validation": [
          {
            "rules": [
              {
                "flag": "presence",
                "constraint": "required"
              }
            ],
            "level": "error"
          }
        ],
        "name": "title",
        "type": "string"
      },
      {
        "name": "tag",
        "type": "string"
      },
      {
        "name": "description",
        "type": "text"
      },
      {
        "name": "icon",
        "type": "string"
      },
      {
        "name": "order",
        "type": "number"
      }
    ],
    "name": "service",
    "type": "document"
  },
  {
    "fields": [
      {
        "validation": [
          {
            "rules": [
              {
                "flag": "presence",
                "constraint": "required"
              }
            ],
            "level": "error"
          }
        ],
        "name": "name",
        "type": "string"
      },
      {
        "name": "badge",
        "type": "string"
      },
      {
        "name": "description",
        "type": "text"
      },
      {
        "name": "statValue",
        "type": "string"
      },
      {
        "name": "statLabel",
        "type": "string"
      },
      {
        "name": "order",
        "type": "number"
      }
    ],
    "name": "fund",
    "type": "document"
  },
  {
    "fields": [
      {
        "validation": [
          {
            "rules": [
              {
                "flag": "presence",
                "constraint": "required"
              }
            ],
            "level": "error"
          }
        ],
        "name": "title",
        "type": "string"
      },
      {
        "options": {
          "list": [
            {
              "title": "Agriculture",
              "value": "agriculture"
            },
            {
              "title": "Energy",
              "value": "energy"
            },
            {
              "title": "Digital",
              "value": "digital"
            },
            {
              "title": "SME",
              "value": "sme"
            }
          ]
        },
        "name": "sector",
        "type": "string"
      },
      {
        "name": "description",
        "type": "text"
      },
      {
        "name": "investmentRange",
        "type": "string"
      },
      {
        "name": "stage",
        "type": "string"
      },
      {
        "initialValue": true,
        "name": "active",
        "type": "boolean"
      }
    ],
    "name": "opportunity",
    "type": "document"
  },
  {
    "fields": [
      {
        "validation": [
          {
            "rules": [
              {
                "flag": "presence",
                "constraint": "required"
              }
            ],
            "level": "error"
          }
        ],
        "name": "title",
        "type": "string"
      },
      {
        "name": "description",
        "type": "text"
      },
      {
        "options": {
          "list": [
            {
              "title": "Forms",
              "value": "Forms"
            },
            {
              "title": "Brochures",
              "value": "Brochures"
            },
            {
              "title": "Reports",
              "value": "Reports"
            },
            {
              "title": "Policies",
              "value": "Policies"
            }
          ]
        },
        "name": "category",
        "type": "string"
      },
      {
        "options": {
          "accept": ".pdf,.doc,.docx,.xls,.xlsx"
        },
        "name": "file",
        "type": "file"
      },
      {
        "name": "publishedDate",
        "type": "date"
      }
    ],
    "name": "bfsDocument",
    "type": "document",
    "title": "Document"
  },
  {
    "fields": [
      {
        "validation": [
          {
            "rules": [
              {
                "flag": "presence",
                "constraint": "required"
              }
            ],
            "level": "error"
          }
        ],
        "name": "title",
        "type": "string"
      },
      {
        "options": {
          "source": "title",
          "maxLength": 96
        },
        "validation": [
          {
            "rules": [
              {
                "flag": "custom"
              },
              {
                "flag": "presence",
                "constraint": "required"
              }
            ],
            "level": "error"
          }
        ],
        "name": "slug",
        "type": "slug"
      },
      {
        "name": "excerpt",
        "type": "text"
      },
      {
        "of": [
          {
            "marks": {
              "annotations": [
                {
                  "i18nTitleKey": "inputs.portable-text.annotation.link",
                  "options": {
                    "modal": {
                      "type": "popover"
                    }
                  },
                  "fields": [
                    {
                      "validation": [
                        {
                          "rules": [
                            {
                              "flag": "uri",
                              "constraint": {
                                "options": {
                                  "scheme": [
                                    "/^http$/",
                                    "/^https$/",
                                    "/^tel$/",
                                    "/^mailto$/"
                                  ],
                                  "allowRelative": true,
                                  "relativeOnly": false,
                                  "allowCredentials": false
                                }
                              }
                            }
                          ],
                          "level": "error"
                        }
                      ],
                      "description": "A valid web, email, phone, or relative link.",
                      "name": "href",
                      "type": "url",
                      "title": "Link"
                    }
                  ],
                  "name": "link",
                  "type": "object"
                }
              ],
              "decorators": [
                {
                  "value": "strong",
                  "title": "Strong"
                },
                {
                  "value": "em",
                  "title": "Italic"
                },
                {
                  "value": "code",
                  "title": "Code"
                },
                {
                  "value": "underline",
                  "title": "Underline"
                },
                {
                  "value": "strike-through",
                  "title": "Strike"
                }
              ]
            },
            "lists": [
              {
                "value": "bullet",
                "title": "Bulleted list"
              },
              {
                "value": "number",
                "title": "Numbered list"
              }
            ],
            "styles": [
              {
                "value": "normal",
                "title": "Normal"
              },
              {
                "value": "h1",
                "title": "Heading 1"
              },
              {
                "value": "h2",
                "title": "Heading 2"
              },
              {
                "value": "h3",
                "title": "Heading 3"
              },
              {
                "value": "h4",
                "title": "Heading 4"
              },
              {
                "value": "h5",
                "title": "Heading 5"
              },
              {
                "value": "h6",
                "title": "Heading 6"
              },
              {
                "value": "blockquote",
                "title": "Quote"
              }
            ],
            "of": [],
            "type": "block"
          }
        ],
        "name": "body",
        "type": "array"
      },
      {
        "options": {
          "hotspot": true
        },
        "name": "coverImage",
        "type": "image"
      },
      {
        "name": "publishedDate",
        "type": "datetime"
      },
      {
        "name": "author",
        "type": "string"
      }
    ],
    "name": "newsPost",
    "type": "document"
  },
  {
    "fields": [
      {
        "validation": [
          {
            "rules": [
              {
                "flag": "presence",
                "constraint": "required"
              }
            ],
            "level": "error"
          }
        ],
        "name": "title",
        "type": "string"
      },
      {
        "name": "location",
        "type": "string"
      },
      {
        "options": {
          "list": [
            {
              "title": "Full-time",
              "value": "Full-time"
            },
            {
              "title": "Contract",
              "value": "Contract"
            },
            {
              "title": "Part-time",
              "value": "Part-time"
            }
          ]
        },
        "name": "type",
        "type": "string"
      },
      {
        "name": "closingDate",
        "type": "date"
      },
      {
        "name": "description",
        "type": "text"
      },
      {
        "initialValue": true,
        "name": "active",
        "type": "boolean"
      }
    ],
    "name": "career",
    "type": "document"
  },
  {
    "fields": [
      {
        "validation": [
          {
            "rules": [
              {
                "flag": "presence",
                "constraint": "required"
              }
            ],
            "level": "error"
          }
        ],
        "name": "name",
        "type": "string"
      },
      {
        "name": "role",
        "type": "string"
      },
      {
        "name": "initials",
        "type": "string"
      },
      {
        "name": "photo",
        "type": "image"
      },
      {
        "name": "order",
        "type": "number"
      }
    ],
    "name": "teamMember",
    "type": "document"
  },
  {
    "fields": [
      {
        "validation": [
          {
            "rules": [
              {
                "flag": "presence",
                "constraint": "required"
              }
            ],
            "level": "error"
          }
        ],
        "name": "label",
        "type": "string"
      },
      {
        "name": "value",
        "type": "number"
      },
      {
        "name": "prefix",
        "type": "string"
      },
      {
        "name": "suffix",
        "type": "string"
      },
      {
        "name": "order",
        "type": "number"
      }
    ],
    "name": "impactStat",
    "type": "document"
  }
]